reliz/__init__.py
reliz/api.py
reliz/app.py
reliz/cli.py
reliz/config.py
reliz/db.py
reliz/errors.py
reliz/front.py
reliz/log.py
reliz/utils.py
reliz/templates/__init__.py
reliz-0.1.0.dev0.dist-info/DESCRIPTION.rst
reliz-0.1.0.dev0.dist-info/METADATA
reliz-0.1.0.dev0.dist-info/RECORD
reliz-0.1.0.dev0.dist-info/WHEEL
reliz-0.1.0.dev0.dist-info/entry_points.txt
reliz-0.1.0.dev0.dist-info/metadata.json
reliz-0.1.0.dev0.dist-info/top_level.txt
